diffplus/__init__.py
diffplus/incremental_diff.py
diffplus/indented_config.py
diffplus-1.3.0.dist-info/METADATA
diffplus-1.3.0.dist-info/WHEEL
diffplus-1.3.0.dist-info/licenses/LICENSE
diffplus-1.3.0.dist-info/RECORD
