Metadata-Version: 2.3
Name: diffplus
Version: 1.3.0
Summary: Incremental and contextual diff between two indented configs
Project-URL: Homepage, https://github.com/angely-dev/diffplus
Project-URL: Bug Tracker, https://github.com/angely-dev/diffplus/issues
Author-email: angely-dev <contact@brindereseau.fr>
License-File: LICENSE
Classifier: License :: OSI Approved :: MIT License
Classifier: Operating System :: OS Independent
Classifier: Programming Language :: Python :: 3
Requires-Python: >=3.8
